geonaksaa/__init__.py
geonaksaa/common.py
geonaksaa/geonaksaa.py
geonaksaa-0.0.1.dist-info/licenses/LICENSE
geonaksaa-0.0.1.dist-info/METADATA
geonaksaa-0.0.1.dist-info/WHEEL
geonaksaa-0.0.1.dist-info/entry_points.txt
geonaksaa-0.0.1.dist-info/top_level.txt
geonaksaa-0.0.1.dist-info/RECORD
